furiosa/litmus/__init__.py
furiosa/litmus/git_version.txt
furiosa/litmus/py.typed
furiosa/litmus/reporter.py
furiosa_litmus-0.10.2.dist-info/entry_points.txt
furiosa_litmus-0.10.2.dist-info/WHEEL
furiosa_litmus-0.10.2.dist-info/METADATA
furiosa_litmus-0.10.2.dist-info/RECORD
